gentrig.cpython-311-darwin.so
gentrig-0.1.2.dist-info/RECORD
gentrig-0.1.2.dist-info/WHEEL
gentrig-0.1.2.dist-info/top_level.txt
gentrig-0.1.2.dist-info/METADATA
gentrig-0.1.2.dist-info/licenses/LICENSE
