Metadata-Version: 2.4
Name: gentrig
Version: 0.1.2
Summary: Trigonometric functions generalized for parabolas and polygons
Author: Alexander Joseph, Joshua Piety
Author-email: Katherine Rose <kiarc@kiarc.win>
Requires-Python: >=3.8
License-File: LICENSE
Requires-Dist: numpy
Dynamic: license-file
